{
    "productDetail": {
        "productId": 117,
        "productName": "Asistencia de salud mensual",
        "policyTypeName": "Asistencias",
        "insuranceCompanyName": "Andi Asistencia"
    },
    "policyHolder": 
        {
            "firstName": "Usuario",
            "secondName": "Prueba",
            "lastName": "Sekure",
            "secondLastName": "Latam",
            "birthdate": "2022-02-18T00:00:00Z",
            "gender": "m",
            "address": "Carrera 100 # 134 -10",
            "identificationType": "1",
            "identificationNumber": "1078985631",
            "maritalStatus": "1",
            "email": "prueba@email.com",
            "phoneNumber": "3154789856"
        },      
    "parameters": [
            {
            "name": "Cédula de Ciudadanía",
            "inputParameterId": 403,
            "inputParameterType": "Text",
            "inputParameterValue": "1078985631",
            "inputParameterDescription": "Cédula de ciudadanía",
            "inputParameterRequired": "true",
            "showApi": true,
            "inputParameterSchemaList": []
        },
        {
            "name": "Celular",
            "inputParameterId": 404,
            "inputParameterType": "Text",
            "inputParameterValue": "3154789856",
            "inputParameterDescription": "Celular",
            "inputParameterRequired": "true",
            "showApi": true,
            "inputParameterSchemaList": []
        }
    
    ]
    
}